labelpoints/__init__.py
labelpoints/__main__.py
labelpoints/app.py
labelpoints/label_file.py
labelpoints/logger.py
labelpoints/shape.py
labelpoints/testing.py
labelpoints/cli/__init__.py
labelpoints/cli/draw_json.py
labelpoints/cli/draw_label_png.py
labelpoints/cli/json_to_dataset.py
labelpoints/cli/on_docker.py
labelpoints/config/__init__.py
labelpoints/config/default_config.yaml
labelpoints/icons/cancel.png
labelpoints/icons/close.png
labelpoints/icons/color-line.png
labelpoints/icons/color.png
labelpoints/icons/copy.png
labelpoints/icons/delete.png
labelpoints/icons/done.png
labelpoints/icons/done.svg
labelpoints/icons/edit.png
labelpoints/icons/expert.png
labelpoints/icons/eye.png
labelpoints/icons/feBlend-icon.png
labelpoints/icons/file.png
labelpoints/icons/fit-width.png
labelpoints/icons/fit-window.png
labelpoints/icons/fit.png
labelpoints/icons/help.png
labelpoints/icons/icon.icns
labelpoints/icons/icon.ico
labelpoints/icons/icon.png
labelpoints/icons/labels.png
labelpoints/icons/labels.svg
labelpoints/icons/new.png
labelpoints/icons/next.png
labelpoints/icons/objects.png
labelpoints/icons/open.png
labelpoints/icons/open.svg
labelpoints/icons/prev.png
labelpoints/icons/quit.png
labelpoints/icons/save-as.png
labelpoints/icons/save-as.svg
labelpoints/icons/save.png
labelpoints/icons/save.svg
labelpoints/icons/undo-cross.png
labelpoints/icons/undo.png
labelpoints/icons/zoom-in.png
labelpoints/icons/zoom-out.png
labelpoints/icons/zoom.png
labelpoints/utils/__init__.py
labelpoints/utils/_io.py
labelpoints/utils/image.py
labelpoints/utils/qt.py
labelpoints/utils/shape.py
labelpoints/widgets/__init__.py
labelpoints/widgets/brightness_contrast_dialog.py
labelpoints/widgets/canvas.py
labelpoints/widgets/color_dialog.py
labelpoints/widgets/escapable_qlist_widget.py
labelpoints/widgets/label_dialog.py
labelpoints/widgets/label_list_widget.py
labelpoints/widgets/tool_bar.py
labelpoints/widgets/unique_label_qlist_widget.py
labelpoints/widgets/zoom_widget.py
labelpoints-0.1.1.2.dist-info/LICENSE
labelpoints-0.1.1.2.dist-info/METADATA
labelpoints-0.1.1.2.dist-info/WHEEL
labelpoints-0.1.1.2.dist-info/entry_points.txt
labelpoints-0.1.1.2.dist-info/top_level.txt
labelpoints-0.1.1.2.dist-info/RECORD
